bn-test-hello/__init__.py
bn-test-hello/main.py
bn_test_hello/__init__.py
bn_test_hello/main.py
hello/__init__.py
hello/main.py
bn_test_hello-0.0.1.dist-info/METADATA
bn_test_hello-0.0.1.dist-info/WHEEL
bn_test_hello-0.0.1.dist-info/top_level.txt
bn_test_hello-0.0.1.dist-info/RECORD
